{
  "project_info": {
    "project_number": "826129402858",
    "firebase_url": "https://petme-2955a-default-rtdb.firebaseio.com",
    "project_id": "petme-2955a",
    "storage_bucket": "petme-2955a.appspot.com"
  },
  "client": [
    {
      "client_info": {
        "mobilesdk_app_id": "1:826129402858:android:8fcb7acbd5e4e2c34b0093",
        "android_client_info": {
          "package_name": "com.example.merge"
        }
      },
      "oauth_client": [],
      "api_key": [
        {
          "current_key": "AIzaSyD0r9XPsAseqjKcynl9drxEI5rDXLP9N1I"
        }
      ],
      "services": {
        "appinvite_service": {
          "other_platform_oauth_client": []
        }
      }
    },
    {
      "client_info": {
        "mobilesdk_app_id": "1:826129402858:android:92818b457b51ad9b4b0093",
        "android_client_info": {
          "package_name": "com.example.petme"
        }
      },
      "oauth_client": [],
      "api_key": [
        {
          "current_key": "AIzaSyD0r9XPsAseqjKcynl9drxEI5rDXLP9N1I"
        }
      ],
      "services": {
        "appinvite_service": {
          "other_platform_oauth_client": []
        }
      }
    }
  ],
  "configuration_version": "1"
}